raindrip/app.py
raindrip/cli.py
raindrip/config.py
raindrip/consumer.py
raindrip/exceptions.py
raindrip/metrics/__init__.py
raindrip/metrics/base.py
raindrip/metrics/hardware.py
raindrip/metrics/network.py
raindrip/metrics/system.py
raindrip/publisher.py
raindrip-0.0.5.dist-info/entry_points.txt
raindrip-0.0.5.dist-info/WHEEL
raindrip-0.0.5.dist-info/METADATA
raindrip-0.0.5.dist-info/RECORD
